{
  "sync_timestamp": "2026-01-12T18:31:48.327Z",
  "profile_name": "Harvad Li",
  "new_posts_synced": 1,
  "images_downloaded": 1,
  "total_posts_in_system": 66,
  "api_status": "working",
  "api_method": "linkedinscraper-rapidapi",
  "next_sync_recommended": "2026-01-12T19:01:48.327Z",
  "new_posts": [
    {
      "title": "New Year, New Project No.3: Invoice Handling System\nFinally freed my hands from invoice processing h...",
      "link": "https://www.linkedin.com/posts/hzl_smes-fintech-fintech-activity-7416175599196463104-Ac7j?utm_source=social_share_send&utm_medium=member_desktop_web&rcm=ACoAABWNEOYBdb1mUVFywmMzK0UKcw_6cTpqScY",
      "has_image": true,
      "engagement": {
        "likes": 3,
        "comments": 0,
        "shares": 1
      },
      "sync_date": "2026-01-12T18:31:48.229Z"
    }
  ]
}